CrossRename/__init__.py
CrossRename/main.py
CrossRename/utils.py
crossrename-1.3.0.dist-info/licenses/LICENSE
crossrename-1.3.0.dist-info/METADATA
crossrename-1.3.0.dist-info/WHEEL
crossrename-1.3.0.dist-info/entry_points.txt
crossrename-1.3.0.dist-info/top_level.txt
crossrename-1.3.0.dist-info/RECORD
