Metadata-Version: 2.4
Name: CrossRename
Version: 1.3.0
Summary: Harmonize file and directory names for Linux and Windows.
Author-email: "Emmanuel C. Jemeni" <jemenichinonso11@gmail.com>
License-Expression: MIT
Project-URL: Homepage, https://github.com/Jemeni11/CrossRename
Project-URL: Bug Tracker, https://github.com/Jemeni11/CrossRename/issues
Project-URL: Changelog, https://github.com/Jemeni11/CrossRename/blob/master/CHANGELOG.md
Project-URL: Funding, https://buymeacoffee.com/jemeni11
Keywords: files,folders,rename,linux,windows,transferring,filename
Classifier: Development Status :: 5 - Production/Stable
Classifier: Environment :: Console
Classifier: Natural Language :: English
Classifier: Programming Language :: Python :: 3
Requires-Python: >=3.9
License-File: LICENSE
Dynamic: license-file
